quick_algo/__init__.py
quick_algo/di_graph.cp311-win_amd64.pyd
quick_algo/di_graph.cpp
quick_algo/di_graph.pyi
quick_algo/pagerank.cp311-win_amd64.pyd
quick_algo/pagerank.cpp
quick_algo/pagerank.pyi
quick_algo/cpp/di_graph.hpp
quick_algo/cpp/di_graph_impl.cpp
quick_algo/cpp/pagerank.hpp
quick_algo/cpp/pagerank_impl.cpp
quick_algo/cpp/pagerank_impl_test.cpp
quick_algo-0.1.3.dist-info/licenses/LICENSE.txt
quick_algo-0.1.3.dist-info/METADATA
quick_algo-0.1.3.dist-info/WHEEL
quick_algo-0.1.3.dist-info/top_level.txt
quick_algo-0.1.3.dist-info/RECORD
