Metadata-Version: 2.4
Name: quick-algo
Version: 0.1.3
Summary: A fast and efficient algorithm library for LPMM
Author-email: Oct-autumn <octautumn2002@gmail.com>
License-Expression: MIT
Project-URL: Homepage, https://github.com/MaiM-with-u/MaiMBot-LPMM
Project-URL: Issues, https://github.com/MaiM-with-u/MaiMBot-LPMM/issues
Classifier: Development Status :: 3 - Alpha
Classifier: Programming Language :: C++
Classifier: Programming Language :: Cython
Classifier: Programming Language :: Python
Classifier: Programming Language :: Python :: 3
Classifier: Programming Language :: Python :: 3.10
Classifier: Programming Language :: Python :: 3.11
Classifier: Programming Language :: Python :: 3.12
Classifier: Programming Language :: Python :: 3.13
Classifier: Programming Language :: Python :: Implementation :: CPython
Requires-Python: >=3.10
License-File: LICENSE.txt
Provides-Extra: build
Requires-Dist: cython; extra == "build"
Requires-Dist: build; extra == "build"
Requires-Dist: setuptools; extra == "build"
Requires-Dist: py-cpuinfo; extra == "build"
Requires-Dist: wheel; extra == "build"
Provides-Extra: test
Requires-Dist: pytest; extra == "test"
Requires-Dist: numpy; extra == "test"
Requires-Dist: scipy; extra == "test"
Requires-Dist: networkx; extra == "test"
Dynamic: license-file
